odoo/addons/generate_pos_orders_ddaa/README.md
odoo/addons/generate_pos_orders_ddaa/__init__.py
odoo/addons/generate_pos_orders_ddaa/__manifest__.py
odoo/addons/generate_pos_orders_ddaa/models/__init__.py
odoo/addons/generate_pos_orders_ddaa/models/generate_pos_orders_ddaa.py
odoo/addons/generate_pos_orders_ddaa/static/description/icon.png
odoo/addons/generate_pos_orders_ddaa/views/generate_pos_orders_ddaa_view.xml
odoo13_addon_generate_pos_orders_ddaa-13.0.0.0.1.dist-info/METADATA
odoo13_addon_generate_pos_orders_ddaa-13.0.0.0.1.dist-info/WHEEL
odoo13_addon_generate_pos_orders_ddaa-13.0.0.0.1.dist-info/top_level.txt
odoo13_addon_generate_pos_orders_ddaa-13.0.0.0.1.dist-info/RECORD
